imgcolorshine/__init__.py
imgcolorshine/__main__.py
imgcolorshine/__version__.py
imgcolorshine/cli.py
imgcolorshine/colorshine.py
imgcolorshine/engine.py
imgcolorshine/falloff.py
imgcolorshine/gamut.py
imgcolorshine/gpu.py
imgcolorshine/io.py
imgcolorshine/lut.py
imgcolorshine/numba_utils.py
imgcolorshine/py.typed
imgcolorshine/trans_numba.py
imgcolorshine/utils.py
imgcolorshine-3.3.3.dist-info/METADATA
imgcolorshine-3.3.3.dist-info/WHEEL
imgcolorshine-3.3.3.dist-info/entry_points.txt
imgcolorshine-3.3.3.dist-info/licenses/LICENSE
imgcolorshine-3.3.3.dist-info/RECORD
