Metadata-Version: 2.4
Name: imgcolorshine
Version: 3.3.3
Project-URL: Documentation, https://github.com/twardoch/imgcolorshine#readme
Project-URL: Issues, https://github.com/twardoch/imgcolorshine/issues
Project-URL: Source, https://github.com/twardoch/imgcolorshine
Author-email: Adam Twardoch <adam+github@twardoch.com>
License: MIT
License-File: LICENSE
Classifier: Development Status :: 4 - Beta
Classifier: Intended Audience :: Developers
Classifier: License :: OSI Approved :: MIT License
Classifier: Operating System :: OS Independent
Classifier: Programming Language :: Python
Classifier: Programming Language :: Python :: 3.10
Classifier: Programming Language :: Python :: 3.11
Classifier: Programming Language :: Python :: 3.12
Classifier: Programming Language :: Python :: Implementation :: CPython
Classifier: Programming Language :: Python :: Implementation :: PyPy
Requires-Python: >=3.10
Requires-Dist: coloraide>=4.6
Requires-Dist: fire>=0.6.0
Requires-Dist: loguru>=0.7.0
Requires-Dist: numba>=0.58.0
Requires-Dist: numpy>=2.2.2
Requires-Dist: opencv-python>=4.8.0
Requires-Dist: pillow>=11.1.0
Requires-Dist: scipy>=1.11.0
Provides-Extra: all
Requires-Dist: absolufy-imports>=0.3.1; extra == 'all'
Requires-Dist: coverage[toml]>=7.6.12; extra == 'all'
Requires-Dist: isort>=6.0.1; extra == 'all'
Requires-Dist: mypy>=1.15.0; extra == 'all'
Requires-Dist: myst-parser>=4.0.0; extra == 'all'
Requires-Dist: pre-commit>=4.1.0; extra == 'all'
Requires-Dist: pytest-asyncio>=0.26.0; extra == 'all'
Requires-Dist: pytest-benchmark[histogram]>=5.1.0; extra == 'all'
Requires-Dist: pytest-cov>=6.0.0; extra == 'all'
Requires-Dist: pytest>=8.3.4; extra == 'all'
Requires-Dist: pyupgrade>=3.19.1; extra == 'all'
Requires-Dist: ruff>=0.9.7; extra == 'all'
Requires-Dist: sphinx-autodoc-typehints>=2.0.0; extra == 'all'
Requires-Dist: sphinx-rtd-theme>=3.0.2; extra == 'all'
Requires-Dist: sphinx>=8.0.0; extra == 'all'
Requires-Dist: ty>=0.0.1a10; extra == 'all'
Provides-Extra: dev
Requires-Dist: absolufy-imports>=0.3.1; extra == 'dev'
Requires-Dist: isort>=6.0.1; extra == 'dev'
Requires-Dist: mypy>=1.15.0; extra == 'dev'
Requires-Dist: pre-commit>=4.1.0; extra == 'dev'
Requires-Dist: pyupgrade>=3.19.1; extra == 'dev'
Requires-Dist: ruff>=0.9.7; extra == 'dev'
Requires-Dist: ty>=0.0.1a10; extra == 'dev'
Provides-Extra: docs
Requires-Dist: myst-parser>=4.0.0; extra == 'docs'
Requires-Dist: sphinx-autodoc-typehints>=3.0.0; extra == 'docs'
Requires-Dist: sphinx-rtd-theme>=3.0.2; extra == 'docs'
Requires-Dist: sphinx>=8.0.0; extra == 'docs'
Provides-Extra: test
Requires-Dist: coverage[toml]>=7.6.12; extra == 'test'
Requires-Dist: pytest-asyncio>=0.26.0; extra == 'test'
Requires-Dist: pytest-benchmark[histogram]>=5.1.0; extra == 'test'
Requires-Dist: pytest-cov>=6.0.0; extra == 'test'
Requires-Dist: pytest>=8.3.4; extra == 'test'
